jsw_scrapy/__init__.py
jsw_scrapy/helpers/alioss_store.py
jsw_scrapy/middlewares/random_user_agent.py
jsw_scrapy/middlewares/request_proxy.py
jsw_scrapy/pipelines/base_pipeline.py
jsw_scrapy-1.0.15.dist-info/METADATA
jsw_scrapy-1.0.15.dist-info/WHEEL
jsw_scrapy-1.0.15.dist-info/RECORD
