Metadata-Version: 2.1
Name: jsw-scrapy
Version: 1.0.15
Summary: Jsw for scrapy.
Home-page: https://js.work
Author: feizheng
Author-email: 1290657123@qq.com
Requires-Python: >=3.7,<4.0
Classifier: Programming Language :: Python :: 3
Classifier: Programming Language :: Python :: 3.7
Classifier: Programming Language :: Python :: 3.8
Classifier: Programming Language :: Python :: 3.9
Classifier: Programming Language :: Python :: 3.10
Classifier: Programming Language :: Python :: 3.11
Requires-Dist: oss2 (>=2.16.0,<3.0.0)
Project-URL: Repository, https://github.com/aric-pypi/jsw-scrapy
